CHANGELOG.md
MANIFEST.in
README.md
install-requirements.txt
setup.py
coverage_mercurial/__init__.py
coverage_mercurial/tests/__init__.py
coverage_mercurial/tests/test_regexps.py
mercurial_testhelpers/__init__.py
mercurial_testhelpers/command.py
mercurial_testhelpers/datetime.py
mercurial_testhelpers/extension.py
mercurial_testhelpers/repo_wrapper.py
mercurial_testhelpers/ui.py
mercurial_testhelpers/util.py
mercurial_testhelpers.egg-info/PKG-INFO
mercurial_testhelpers.egg-info/SOURCES.txt
mercurial_testhelpers.egg-info/dependency_links.txt
mercurial_testhelpers.egg-info/requires.txt
mercurial_testhelpers.egg-info/top_level.txt
mercurial_testhelpers/tests/__init__.py
mercurial_testhelpers/tests/test_command.py
mercurial_testhelpers/tests/test_extension.py
mercurial_testhelpers/tests/test_repo_wrapper.py
mercurial_testhelpers/tests/test_using_extensions.py