Metadata-Version: 2.1
Name: mercurial-testhelpers
Version: 0.7.1
Summary: Helpers to write Python tests involving Python internals of Mercurial
Author: Georges Racinet
Author-email: georges.racinet@octobus.net
License: GPLv2+
Project-URL: Source, https://foss.heptapod.net/mercurial/testhelpers
Project-URL: Tracker, https://foss.heptapod.net/mercurial/testhelpers/-/issues
Keywords: hg mercurial testing
Classifier: Development Status :: 4 - Beta
Classifier: License :: OSI Approved :: GNU General Public License v2 or later (GPLv2+)
Classifier: Programming Language :: Python :: 2.7
Classifier: Programming Language :: Python :: 3.7
Classifier: Programming Language :: Python :: 3.8
Classifier: Programming Language :: Python :: 3.9
Classifier: Topic :: Software Development :: Testing
Classifier: Topic :: Software Development :: Version Control :: Mercurial
Requires-Dist: mercurial
Requires-Dist: coverage
